{"completed":false,"fixtures":[{"awayGoals":0,"awayTeam":{"name":"Crystal Palace"},"date":"\/Date(1330433100000+0000)\/","homeGoals":0,"homeTeam":{"name":"West Ham"},"played":false},{"awayGoals":0,"awayTeam":{"name":"Swansea"},"date":"\/Date(1330441200000+0000)\/","homeGoals":0,"homeTeam":{"name":"Burnley"},"played":false},{"awayGoals":0,"awayTeam":{"name":"Sunderland"},"date":"\/Date(1330441200000+0000)\/","homeGoals":0,"homeTeam":{"name":"Man Utd"},"played":false},{"awayGoals":0,"awayTeam":{"name":"Aston Villa"},"date":"\/Date(1330441200000+0000)\/","homeGoals":0,"homeTeam":{"name":"Newcastle"},"played":false},{"awayGoals":0,"awayTeam":{"name":"Hull"},"date":"\/Date(1330441200000+0000)\/","homeGoals":0,"homeTeam":{"name":"Stoke"},"played":false},{"awayGoals":0,"awayTeam":{"name":"Southampton"},"date":"\/Date(1330441200000+0000)\/","homeGoals":0,"homeTeam":{"name":"West Brom"},"played":false},{"awayGoals":0,"awayTeam":{"name":"Man City"},"date":"\/Date(1330603200000+0000)\/","homeGoals":0,"homeTeam":{"name":"Liverpool"},"played":false},{"awayGoals":0,"awayTeam":{"name":"Everton"},"date":"\/Date(1330610700000+0000)\/","homeGoals":0,"homeTeam":{"name":"Arsenal"},"played":false}],"started":false}