{"transfers_out": 8094, "code": 324568, "event_total": 1, "last_season_points": 0, "squad_number": null, "transfers_balance": 5575, "news_updated": null, "event_cost": 50, "news_added": "2012-08-13T20:30:15 UTC+0000", "web_name": "Gibson", "in_dreamteam": false, "team_code": 324568, "id": 108, "shirt_image_url": "http://cdn.ismfg.net/static/plfpl/img/shirts/shirt_4.png", "first_name": "Darron", "transfers_out_event": 3461, "element_type_id": 3, "max_cost": 50, "event_explain": [["Minutes played", 19, 1]], "selected": 30912, "min_cost": 50, "fixtures": {"all": [["17 Sep 20:00", "Gameweek 4", "Newcastle (H)"], ["22 Sep 12:45", "Gameweek 5", "Swansea (A)"], ["29 Sep 15:00", "Gameweek 6", "Southampton (H)"], ["06 Oct 15:00", "Gameweek 7", "Wigan (A)"], ["21 Oct 16:00", "Gameweek 8", "QPR (A)"], ["28 Oct 13:30", "Gameweek 9", "Liverpool (H)"], ["03 Nov 15:00", "Gameweek 10", "Fulham (A)"], ["10 Nov 15:00", "Gameweek 11", "Sunderland (H)"], ["17 Nov 15:00", "Gameweek 12", "Reading (A)"], ["24 Nov 15:00", "Gameweek 13", "Norwich (H)"], ["28 Nov 19:45", "Gameweek 14", "Arsenal (H)"], ["01 Dec 15:00", "Gameweek 15", "Man City (A)"], ["09 Dec 15:00", "Gameweek 16", "Tottenham (H)"], ["15 Dec 15:00", "Gameweek 17", "Stoke City (A)"], ["22 Dec 15:00", "Gameweek 18", "West Ham (A)"], ["26 Dec 15:00", "Gameweek 19", "Wigan (H)"], ["29 Dec 15:00", "Gameweek 20", "Chelsea (H)"], ["01 Jan 15:00", "Gameweek 21", "Newcastle (A)"], ["12 Jan 15:00", "Gameweek 22", "Swansea (H)"], ["19 Jan 15:00", "Gameweek 23", "Southampton (A)"], ["30 Jan 19:45", "Gameweek 24", "West Brom (H)"], ["02 Feb 15:00", "Gameweek 25", "Aston Villa (H)"], ["09 Feb 15:00", "Gameweek 26", "Man Utd (A)"], ["23 Feb 15:00", "Gameweek 27", "Norwich (A)"], ["02 Mar 15:00", "Gameweek 28", "Reading (H)"], ["09 Mar 15:00", "Gameweek 29", "Arsenal (A)"], ["16 Mar 15:00", "Gameweek 30", "Man City (H)"], ["30 Mar 15:00", "Gameweek 31", "Stoke City (H)"], ["06 Apr 15:00", "Gameweek 32", "Tottenham (A)"], ["13 Apr 15:00", "Gameweek 33", "QPR (H)"], ["20 Apr 15:00", "Gameweek 34", "Sunderland (A)"], ["27 Apr 15:00", "Gameweek 35", "Fulham (H)"], ["04 May 15:00", "Gameweek 36", "Liverpool (A)"], ["12 May 15:00", "Gameweek 37", "West Ham (H)"], ["19 May 15:00", "Gameweek 38", "Chelsea (A)"]], "summary": [[4, "NEW (H)", "17 Sep 20:00"], [5, "SWA (A)", "22 Sep 12:45"], [6, "SOU (H)", "29 Sep 15:00"]]}, "season_history": [["2007/08", 0, 0, 0, 0, 0, 0, 0, 0, 0, 0, 0, 0, 0, 43, 0], ["2008/09", 140, 1, 0, 0, 0, 0, 0, 0, 1, 0, 0, 3, 0, 50, 12], ["2009/10", 595, 2, 3, 0, 2, 0, 0, 0, 2, 0, 0, 0, 0, 46, 40], ["2010/11", 657, 0, 1, 3, 8, 0, 0, 0, 3, 0, 0, 0, 0, 49, 21], ["2011/12", 1015, 1, 2, 5, 10, 0, 0, 0, 3, 0, 0, 3, 156, 51, 39]], "total_points": 9, "type_name": "Midfielder", "team_name": "Everton", "status": "a", "added": "2012-07-17T15:37:20 UTC+0000", "form": 3.0, "shirt_mobile_image_url": "http://cdn.ismfg.net/static/plfpl/img/shirts/mobile/shirt_4.png", "current_fixture": "West Brom (A)", "now_cost": 50, "points_per_game": 3.0, "transfers_in": 16344, "news": "", "original_cost": 50, "event_points": 1, "news_return": null, "fixture_history": {"all": [["20 Aug 20:00", 1, "MUN(H) 1-0", 90, 0, 1, 1, 0, 0, 0, 0, 1, 0, 0, 0, 9, 0, 50, 5], ["25 Aug 15:00", 2, "AVL(A) 3-1", 69, 0, 0, 1, 0, 0, 0, 0, 0, 0, 0, 0, 4, 5053, 50, 3], ["01 Sep 15:00", 3, "WBA(A) 0-2", 19, 0, 0, 0, 0, 0, 0, 0, 0, 0, 0, 0, 2, 5088, 50, 1]], "summary": [[1, "MUN (H)", 5], [2, "AVL (A)", 3], [3, "WBA (A)", 1]]}, "next_fixture": "Newcastle (H)", "transfers_in_event": 1570, "selected_by": "1.3", "team_id": 4, "second_name": "Gibson", "photo_mobile_url": "http://cdn.ismfg.net/static/plfpl/img/shirts/photos/324568.jpg"}